setup.py
src/python_openapi3/__init__.py
src/python_openapi3/_util.py
src/python_openapi3/logger.py
src/python_openapi3/oas_metabase_py2.py
src/python_openapi3/oas_metabase_py3.py
src/python_openapi3/oasmetabase_util.py
src/python_openapi3/pycompat23_local.py
src/python_openapi3/schema.py
src/python_openapi3.egg-info/PKG-INFO
src/python_openapi3.egg-info/SOURCES.txt
src/python_openapi3.egg-info/dependency_links.txt
src/python_openapi3.egg-info/requires.txt
src/python_openapi3.egg-info/top_level.txt
src/python_openapi3/openapi_specification/__init__.py
src/python_openapi3/openapi_specification/component_section.py
src/python_openapi3/openapi_specification/info_section.py
src/python_openapi3/openapi_specification/oas_definitions.py
src/python_openapi3/openapi_specification/oas_parameters.py
src/python_openapi3/openapi_specification/oas_response.py
src/python_openapi3/openapi_specification/oas_server.py
src/python_openapi3/openapi_specification/paths_sections.py
src/python_openapi3/openapi_specification/root.py